i38e_utils/__init__.py
i38e_utils/data_utils.py
i38e_utils/date_utils.py
i38e_utils/df_helper/__init__.py
i38e_utils/df_helper/_df_helper.py
i38e_utils/df_helper/_parquet_artifact.py
i38e_utils/df_helper/config.py
i38e_utils/df_helper/io.py
i38e_utils/df_helper/models.py
i38e_utils/df_helper/sql_model_builder.py
i38e_utils/df_helper/utils.py
i38e_utils/df_utils.py
i38e_utils/file_utils.py
i38e_utils/geopy_helper/__init__.py
i38e_utils/geopy_helper/geolocation_service.py
i38e_utils/geopy_helper/utils.py
i38e_utils/log_utils.py
i38e_utils/osmnx_helper/__init__.py
i38e_utils/osmnx_helper/_base_osm_map.py
i38e_utils/osmnx_helper/utils.py
i38e_utils-1.0.48.dist-info/METADATA
i38e_utils-1.0.48.dist-info/WHEEL
i38e_utils-1.0.48.dist-info/RECORD
