Metadata-Version: 2.1
Name: i38e-utils
Version: 1.0.48
Summary: Utilities for IBIS applications in data science and engineering
Author: Luis Valverde
Author-email: lvalverdeb@gmail.com
Requires-Python: >=3.10,<3.13
Classifier: Programming Language :: Python :: 3
Classifier: Programming Language :: Python :: 3.10
Classifier: Programming Language :: Python :: 3.11
Classifier: Programming Language :: Python :: 3.12
Requires-Dist: dask[complete] (>=2024.3.0,<2025.0.0)
Requires-Dist: django (==4.1.13)
Requires-Dist: folium (>=0.17.0,<0.18.0)
Requires-Dist: geopy (>=2.4.1,<3.0.0)
Requires-Dist: openpyxl (>=3.1.2,<4.0.0)
Requires-Dist: osmnx (>=1.9.4,<2.0.0)
Requires-Dist: pandas (>=2.1.4,<3.0.0)
Requires-Dist: pydantic (>=2.6.4,<3.0.0)
Requires-Dist: tomli (>=2.0.1,<3.0.0)
Requires-Dist: tqdm (>=4.66.5,<5.0.0)
